{"id":"abu-talat-egypt","name":"Abu Talat, Egypt","country":"Egypt","cables":[{"id":"asia-africa-europe-1-aae-1","name":"Asia Africa Europe-1 (AAE-1)","rfs_year":2017,"is_planned":false},{"id":"europe-india-gateway-eig","name":"Europe India Gateway (EIG)","rfs_year":2011,"is_planned":false},{"id":"middle-east-north-africa-mena-cable-systemgulf-bridge-international","name":"Middle East North Africa (MENA) Cable System/Gulf Bridge International","rfs_year":2014,"is_planned":false},{"id":"peace-cable","name":"PEACE Cable","rfs_year":2022,"is_planned":false},{"id":"seamewe-5","name":"SeaMeWe-5","rfs_year":2016,"is_planned":false},{"id":"te-northtgn-eurasiaseacomalexandrosmedex","name":"TE North/TGN-Eurasia/SEACOM/Alexandros/Medex","rfs_year":2011,"is_planned":false}],"landing_points":["jeddah-saudi-arabia","zafarana-egypt","abu-talat-egypt","mazara-del-vallo-italy","marseille-france","barka-oman","monaco-monaco","mumbai-india","tripoli-libya","haramous-djibouti","bude-united-kingdom","gibraltar-gibraltar","al-seeb-oman","fujairah-united-arab-emirates","sesimbra-portugal","pentaskhinos-cyprus","chania-greece","djibouti-city-djibouti","karachi-pakistan","doha-qatar","songkhla-thailand","satun-thailand","sihanoukville-cambodia","aden-yemen","al-bustan-oman","toulon-france","catania-italy","yanbu-saudi-arabia","qalhat-oman","ngwe-saung-myanmar","melaka-malaysia","tuas-singapore","kuakata-bangladesh","al-hudaydah-yemen","matara-sri-lanka","bari-italy","marmaris-turkey","dumai-indonesia","medan-indonesia","cape-daguilar-china","vung-tau-vietnam","gwadar-pakistan","mombasa-kenya","victoria-seychelles","bosaso-somalia","mogadishu-somalia","kismayo-somalia","hobyo-somalia","annaba-algeria","yeroskipos-cyprus","mellieha-malta","butterworth-malaysia","kulhudhufushi-maldives"]}
