{"id":"perth-wa-australia","name":"Perth, WA, Australia","country":"Australia","cables":[{"id":"australia-singapore-cable-asc","name":"Australia-Singapore Cable (ASC)","rfs_year":2018,"is_planned":false},{"id":"indigo-central","name":"INDIGO-Central","rfs_year":2019,"is_planned":false},{"id":"indigo-west","name":"INDIGO-West","rfs_year":2019,"is_planned":false},{"id":"oman-australia-cable-oac","name":"Oman Australia Cable (OAC)","rfs_year":2022,"is_planned":true},{"id":"seamewe-3","name":"SeaMeWe-3","rfs_year":1999,"is_planned":false}],"landing_points":["deep-water-bay-china","taipa-china","batangas-philippines","danang-vietnam","tungku-brunei","mersing-malaysia","tuas-singapore","okinawa-japan","shanghai-china","toucheng-taiwan","fangshan-taiwan","ancol-indonesia","perth-wa-australia","penang-malaysia","satun-thailand","pyapon-myanmar","mt-lavinia-sri-lanka","cochin-india","mumbai-india","karachi-pakistan","muscat-oman","fujairah-united-arab-emirates","djibouti-city-djibouti","suez-egypt","alexandria-egypt","yeroskipos-cyprus","marmaris-turkey","mazara-del-vallo-italy","sesimbra-portugal","penmarch-france","goonhilly-downs-united-kingdom","medan-indonesia","jeddah-saudi-arabia","chania-greece","ttouan-morocco","ostend-belgium","alexandria-nsw-australia","jakarta-indonesia","anyer-indonesia","flying-fish-cove-christmas-island","tanah-merah-singapore","geoje-south-korea","west-island-cocos-keeling-islands","shantou-china"]}
