{"id":"san-sebastian-de-la-gomera-canary-islands-spain","name":"San Sebastian de la Gomera, Canary Islands, Spain","country":"Spain","cables":[{"id":"la-gomera-el-hierro","name":"La Gomera-El Hierro","rfs_year":null,"is_planned":false},{"id":"tenerife-la-gomera-la-palma","name":"Tenerife-La Gomera-La Palma","rfs_year":1994,"is_planned":false}],"landing_points":["santa-cruz-de-la-palma-canary-islands-spain","granadilla-canary-islands-spain","san-sebastian-de-la-gomera-canary-islands-spain","valverde-canary-islands-spain"]}
