{"id":"2014","name":"2014","landing_points":["jacksonville-fl-united-states","cancn-mexico","puerto-barrios-guatemala","cartagena-colombia","barranquilla-colombia","puerto-plata-dominican-republic","san-juan-pr-united-states","fortaleza-brazil","rio-de-janeiro-brazil","salvador-brazil","hollywood-fl-united-states","schooner-bight-colombia","largs-united-kingdom","kilchatten-bay-united-kingdom","otter-ferry-united-kingdom","achnaba-united-kingdom","blackwaterfoot-united-kingdom","ardnacross-united-kingdom","down-craig-united-kingdom","corrie-united-kingdom","ardneil-bay-united-kingdom","port-askaig-united-kingdom","feolin-ferry-united-kingdom","lagavulin-united-kingdom","glenbarr-united-kingdom","craighouse-united-kingdom","ormsary-united-kingdom","kilchoan-ferry-united-kingdom","tobermory-united-kingdom","duart-bay-united-kingdom","ganavan-bay-united-kingdom","corran-united-kingdom","ardmair-united-kingdom","branahuie-bay-united-kingdom","leverburgh-united-kingdom","lochmaddy-united-kingdom","dunvegan-united-kingdom","sandwick-village-united-kingdom","ardvasar-united-kingdom","mallaigvaig-united-kingdom","scarinish-united-kingdom","calgary-united-kingdom","ludag-united-kingdom","balla-united-kingdom","north-bay-united-kingdom","bay-of-tuquoy-united-kingdom","aikerness-bay-united-kingdom","portachur-point-united-kingdom","coilleag-united-kingdom","ardbeg-point-united-kingdom","ardyne-point-united-kingdom","ardgour-united-kingdom","kelibia-tunisia","mazara-del-vallo-italy","flores-portugal","corvo-portugal","graciosa-portugal","faial-portugal","port-vila-vanuatu","suva-fiji","porthcurno-united-kingdom","porthcressa-beach-united-kingdom","kuala-tungkal-indonesia","tanjung-pinggir-indonesia","kerch-ukraine","ilyich-russia","jeddah-saudi-arabia","zafarana-egypt","abu-talat-egypt","al-seeb-oman","djibouti-city-djibouti","taytay-philippines","san-jose-de-buenavista-philippines","port-moresby-papua-new-guinea","kikori-papua-new-guinea","pentaskhinos-cyprus","yeroskipos-cyprus","kristiansand-norway","tjele-denmark","palembang-indonesia","muntok-indonesia","tarakan-indonesia","tanjung-selor-indonesia"],"cables":[{"id":"america-movil-submarine-cable-system-1-amx-1","name":"America Movil Submarine Cable System-1 (AMX-1)","rfs_year":2014,"is_planned":false},{"id":"bt-highlands-and-islands-submarine-cable-system","name":"BT Highlands and Islands Submarine Cable System","rfs_year":2014,"is_planned":false},{"id":"didon","name":"Didon","rfs_year":2014,"is_planned":false},{"id":"flores-corvo-cable-system","name":"Flores-Corvo Cable System","rfs_year":2014,"is_planned":false},{"id":"interchange-cable-network-1-icn1","name":"Interchange Cable Network 1 (ICN1)","rfs_year":2014,"is_planned":false},{"id":"isles-of-scilly-cable","name":"Isles of Scilly Cable","rfs_year":2014,"is_planned":false},{"id":"jambi-batam-cable-system-jiba","name":"Jambi-Batam Cable System (JIBA)","rfs_year":2014,"is_planned":false},{"id":"kerch-strait-cable","name":"Kerch Strait Cable","rfs_year":2014,"is_planned":false},{"id":"middle-east-north-africa-mena-cable-systemgulf-bridge-international","name":"Middle East North Africa (MENA) Cable System/Gulf Bridge International","rfs_year":2014,"is_planned":false},{"id":"palawan-iloilo-cable-system","name":"Palawan-Iloilo Cable System","rfs_year":2014,"is_planned":false},{"id":"png-lng","name":"PNG LNG","rfs_year":2014,"is_planned":false},{"id":"poseidon","name":"POSEIDON","rfs_year":2014,"is_planned":false},{"id":"skagerrak-4","name":"Skagerrak 4","rfs_year":2014,"is_planned":false},{"id":"sumatera-bangka-cable-system-sbcs","name":"Sumatera Bangka Cable System (SBCS)","rfs_year":2014,"is_planned":false},{"id":"tarakan-selor-cable-system-tscs","name":"Tarakan Selor Cable System (TSCS)","rfs_year":2014,"is_planned":false}]}
