{"id":"micronesia","name":"Micronesia","cables":[{"id":"chuuk-pohnpei-cable","name":"Chuuk-Pohnpei Cable","rfs_year":2019,"is_planned":false},{"id":"hantru1-cable-system","name":"HANTRU1 Cable System","rfs_year":2010,"is_planned":false},{"id":"sea-us","name":"SEA-US","rfs_year":2017,"is_planned":false}],"landing_points":["majuro-marshall-islands","kwajalein-marshall-islands","pohnpei-micronesia","piti-guam","davao-philippines","hermosa-beach-ca-united-states","makaha-hi-united-states","kauditan-indonesia","magachgil-yap-micronesia","weno-chuuk-micronesia","ngeremlengui-palau"],"landing_points_in_country":["pohnpei-micronesia","magachgil-yap-micronesia","weno-chuuk-micronesia"]}
