{"id":"suriname","name":"Suriname","cables":[{"id":"deep-blue-one","name":"Deep Blue One","rfs_year":2024,"is_planned":true},{"id":"suriname-guyana-submarine-cable-system-sg-scs","name":"Suriname-Guyana Submarine Cable System (SG-SCS)","rfs_year":2010,"is_planned":false}],"landing_points":["chaguaramas-trinidad-and-tobago","georgetown-guyana","totness-suriname","cayenne-french-guiana","paramaribo-suriname","rockly-bay-trinidad-and-tobago"],"landing_points_in_country":["paramaribo-suriname","totness-suriname"]}
